{"About the Company": "The objective of Power Grid Corporation of India Ltd is to create a strong and vibrant national grid in the country to ensure the optimum utilization of generating resources, conservation of an eco-sensitive right of way and the flexibility to accommodate the uncertainty of generation plans.Several milestones have been achieved by Power Grid Corporation of India as a part of the development of the national grid such as the implementation of Asias longest Talcher-Kolar HVDC Bipole link including its upgradation, Sasaram HVDC back-to-back link, 400 kV D/C Synchronous interconnection between Eastern and Western Region including series compensation, augmentation of Gazuwaka HVDC, Muzaffarpur-Gorakhpur 400 kV D/c line under Tala Transmission System, Agra-Gwalior 765 kV S/C line (operating at 400 kV), Patna-Balia 400 kV D/c line, Biharshariff-Balia 400 kV D/c line, etc.Presently, Power Grid is one of the few telecom players with a marked presence in remote areas and is providing highly reliable services to various customers.The company has taken lead role and making valuable contribution in the government of Indias nation building schemes of Accelerated Power Development and Reforms Programme (APDRP) and Rajiv Gandhi Grameen Vidyutikaran Yojana (RGGVY) aimed at bringing qualitative improvement in the distribution sector..The company also in the business segment of Telecom, Consultancy, Transmission.", "address": {"address1": "B-9, Qutab Institutional Area,", "address2": "Katwaria Sarai,,", "city": "New Delhi", "state": "Delhi", "pincode": "110016", "telephone1": "26560112", "telephone2": "26560115", "fax1": "011-26601081", "fax2": "", "email": "investors@powergrid.co.in", "web": "http://www.powergrid.in"}, "management": [{"name": "K Sreekant", "designation": "Chairman & Managing Director"}, {"name": "Ravindra Kumar Tyagi", "designation": "Director - Operations"}, {"name": "Abhay Choudhary", "designation": "Director - Projects"}, {"name": "Ravisankar Ganesan", "designation": "Director - Finance"}, {"name": "Chetan Bansilal Kankariya", "designation": "Independent Director"}], "registrars": {"name": "KFIN Technologies Pvt. Ltd.", "address1": "Selenium Tower B, Plot No. 31-32,", "address2": "Gachibowli, Financial District, \nNanakramguda,Seri", "address3": "", "address4": "", "telephone": "040-67161500, 67162222, 33211000", "fax": "040-23420814, 23001153", "email": "einward.ris@karvy.com", "internet": "http://www.kfintech.com", "city": "Hyderabad", "state": "Telangana", "pincode": "500032"}, "listing": [{"name": "BSE 100", "value": "Yes"}, {"name": "BSE 200", "value": "Yes"}, {"name": "SENSEX", "value": "Yes"}, {"name": "CNX MIDCAP 200", "value": "No"}, {"name": "NIFTY 50", "value": "Yes"}, {"name": "BSE 500", "value": "Yes"}], "details": {"bseId": "532898", "nseId": "POWERGRID", "series": "EQ", "isinid": "INE752E01010"}}