{"About the Company": "Allahabad Bank is oldest nationalised Bank with rich experience in extending various banking solutions to its valued clients. Allahabad Bank is well spread out in India and recently opened first International Branch at Hong Kong. Bank has also arrangements with correspondents at various important overseas locations, which will ensure extending to its all NRI customers rich banking experience. Their products fall under the following broad categories Deposit products, Retail Credit products & other Credit Products like Kisan Credit Card,Kisan Shakti Yojana & AllBank-Expo; services offered include All Ayushman Bima Yojana , Cash Management Services , Depository Services ,Visa Debit Cum ATM Card ,Real Time Gross Settlement (RTGS) ,National Electronic Funds Transfer (NEFT) , Gold Card Scheme for Exporters ,Charter for MSMEs ,Government Business & Regional MSME Care Centres", "address": {"address1": "2, Nethaji Subhas Road,", "address2": ",", "city": "Kolkata", "state": "West Bengal", "pincode": "700001", "telephone1": "033-22420851", "telephone2": "", "fax1": "033-22107424", "fax2": "033-22623279", "email": "investors.grievance@allahabadbank.in", "web": "http://www.allahabadbank.in"}, "management": [{"name": "K Ramachandran", "designation": "Executive Director"}, {"name": "Parthapratim Pal", "designation": "Shareholder Director"}, {"name": "Sarath Sura", "designation": "Shareholder Director"}, {"name": "Bijaya Kumar Sahoo", "designation": "Shareholder Director"}, {"name": "Rajeev Ranjan", "designation": "Government Nominee Director"}], "registrars": {"name": "C B Management Services Ltd.", "address1": "P-22, 2nd Floor,", "address2": "Bondel Road,", "address3": "", "address4": "", "telephone": "033-40116700, 22806692, 22806693, 22806694, 228024", "fax": "033-22870263", "email": "rta@cbmsl.com", "internet": "http://www.cbmsl.com", "city": "Kolkata", "state": "West Bengal", "pincode": "700019"}, "listing": [{"name": "BSE 100", "value": "No"}, {"name": "BSE 200", "value": "No"}, {"name": "SENSEX", "value": "No"}, {"name": "CNX MIDCAP 200", "value": "Yes"}, {"name": "NIFTY 50", "value": "No"}, {"name": "BSE 500", "value": "No"}], "details": {"bseId": "532480", "nseId": "ALBK", "series": "", "isinid": "INE428A01015"}}