{"About the Company": "ABC Gas (International) Limited, has been at the forefront of the international gas industry. The services offered by the company includes Total system design network analysis of distribution system,Supply, installation and commissioning of entire system,Inspection and maintenance of the facility,After sales, service and support,Hand on training to the consumers,Assured continuous supply of LPG in the system.The company is currently engaged in the business of trading gas meter and appliances known as a centralized piped system which supply natural gas.", "address": {"address1": "1, Mahesh Villa,", "address2": "B. G. Kher Road,,Worli,", "city": "Mumbai", "state": "Maharashtra", "pincode": "400018", "telephone1": "022-24935508", "telephone2": "022-24938697", "fax1": "022-24937758", "fax2": "", "email": "pipedgas@gmail.com", "web": "https://www.abcgas.co.in"}, "management": [{"name": "Shyamlal Prasad Shorewala", "designation": "Chairman & Executive Director"}, {"name": "Rohith Satish Shorewala", "designation": "Whole Time Director"}, {"name": "Neelam Satish Shorewala", "designation": "Executive Director"}, {"name": "Yash Ratanlal Mardia", "designation": "Ind. Non-Executive Director"}, {"name": "Akhilesh Singhal", "designation": "Ind. Non-Executive Director"}], "registrars": {"name": "Link Intime India Pvt. Ltd.", "address1": "C 101, 247 Park,\nL.B.S. Marg, Vikhroli (West),", "address2": "", "address3": "", "address4": "", "telephone": "022-49186270, 49186200", "fax": "022-49186060", "email": "rnt.helpdesk@linkintime.co.in", "internet": "http://www.linkintime.co.in", "city": "Mumbai", "state": "Maharashtra", "pincode": "400083"}, "listing": [{"name": "BSE 100", "value": "No"}, {"name": "BSE 200", "value": "No"}, {"name": "SENSEX", "value": "No"}, {"name": "CNX MIDCAP 200", "value": "No"}, {"name": "NIFTY 50", "value": "No"}, {"name": "BSE 500", "value": "No"}], "details": {"bseId": "513119", "nseId": "", "series": "", "isinid": "INE173M01012"}}