{"About the Company": "Shirpur Gold Refinery Ltd (SGRL)has set up a greenfield precious metal refinery.This world-class refinery has the technical capability to refine and fabricate gold and silver up to 999.9 fineness. The company has procured and installed proven refinery technology and equipment.In order to facilitate secured logistics, SGRL has its own airstrip with night landing facilities. The company has established an all-India dealer network for effective distribution.", "address": {"address1": "Refinery Site,", "address2": "Shirpur,", "city": "Dhule Dist.", "state": "Maharashtra", "pincode": "425405", "telephone1": "02562-258002", "telephone2": "02562-258001", "fax1": "02562-261357", "fax2": "", "email": "investorinfo@shirpurgold.com", "web": "http://www.shirpurgold.com"}, "management": [{"name": "Prakash Chandra Pandey", "designation": "Non Exe.Non Ind.Director"}, {"name": "Shankar Bhandari", "designation": "Non Exe.Non Ind.Director"}, {"name": "Suresh Saini", "designation": "Non Exe.Non Ind.Director"}, {"name": "Kavita Kapahi", "designation": "Independent Director"}, {"name": "Anish Goel", "designation": "Independent Director"}], "registrars": {"name": "Link Intime India Pvt. Ltd.", "address1": "C 101, 247 Park,\nL.B.S. Marg, Vikhroli (West),", "address2": "", "address3": "", "address4": "", "telephone": "022-49186270, 49186200", "fax": "022-49186060", "email": "rnt.helpdesk@linkintime.co.in", "internet": "http://www.linkintime.co.in", "city": "Mumbai", "state": "Maharashtra", "pincode": "400083"}, "listing": [{"name": "BSE 100", "value": "No"}, {"name": "BSE 200", "value": "No"}, {"name": "SENSEX", "value": "No"}, {"name": "CNX MIDCAP 200", "value": "No"}, {"name": "NIFTY 50", "value": "No"}, {"name": "BSE 500", "value": "No"}], "details": {"bseId": "512289", "nseId": "SHIRPUR-G", "series": "", "isinid": "INE196B01016"}}