{"About the Company": "Fruition Ventures Limited (FVL) (earlier Indo WebSec Limited (IWSL)) is a leading Industrial and Investment house with interests in trading of computer & computer peripherals, fabrics, shares and securities, consultancy and other related activities.", "address": {"address1": "1301, Padma Tower-1,", "address2": "Rajendra Place,,", "city": "New Delhi", "state": "Delhi", "pincode": "110008", "telephone1": "011-25710171", "telephone2": "", "fax1": "011-47561818", "fax2": "", "email": "cs@fruitionventure.com", "web": "http://www.fruitionventure.com"}, "management": [{"name": "Nitin Aggarwal", "designation": "Managing Director"}, {"name": "Krishan Kumar Aggarwal", "designation": "Non Executive Director"}, {"name": "Tarsem Kumar Jain", "designation": "Independent Director"}, {"name": "Deepika Jain", "designation": "Independent Director"}, {"name": "Sunit Gupta", "designation": "Independent Director"}], "registrars": {"name": "RCMC Share Registry Pvt. Ltd.", "address1": "B-25/1, 1st Floor, Okhla Industrial Area, Phase-II", "address2": "", "address3": "", "address4": "", "telephone": "011-26387320, 26387321", "fax": "", "email": "sectshares@rcmcdelhi.com", "internet": "http://www.rcmcdelhi.com", "city": "New Delhi", "state": "Delhi", "pincode": "110020"}, "listing": [{"name": "BSE 100", "value": "No"}, {"name": "BSE 200", "value": "No"}, {"name": "SENSEX", "value": "No"}, {"name": "CNX MIDCAP 200", "value": "No"}, {"name": "NIFTY 50", "value": "No"}, {"name": "BSE 500", "value": "No"}], "details": {"bseId": "538568", "nseId": "", "series": "", "isinid": "INE836C01015"}}