{"About the Company": "Restile Ceramics Ltd. is a pioneer in vitrified tile and in the business of flooring tiles.Product range of the company includes:Mirror stone-These tiles come in mirror finish which is far superior to all other tiles including natural stones, marble and granite. These tiles are pre-polished and ready to use. It has high glossy finish with true reflective properties. These tiles which are heavy duty, fully vitrified, acid and alkali resistant ,are produced under strict quality controls at the modern plant of Restile at Hyderabad, using very superior quality raw materials. The process involves fine milling, spray drying, dry pressing at high pressures, firing under high temperature under defined process parameters to ensure homogeneous, dense and non-porous tiles.PearlRock-It finish with silky smooth surface, pampers your senses, a caring touch that gives you homely feel. The tiles are best to use in the area where you used to walk on a bare feet like kitchen, living room etc.", "address": {"address1": "204, Sakar Complex,", "address2": "Opp ABS Tower,,Vaccine Crossing,", "city": "Vadodra", "state": "Gujarat", "pincode": "390015", "telephone1": "", "telephone2": "", "fax1": "0265-", "fax2": "", "email": "restile@accountscare.com", "web": "http://www.restile.com"}, "management": [{"name": "Nalinkant Amratlal Rathod", "designation": "Chairman & Non-Exe.Director"}, {"name": "Viren Rathod", "designation": "Managing Director"}, {"name": "Bharathi Nalin Rathod", "designation": "Woman Director"}, {"name": "N S Mani", "designation": "Ind. Non-Executive Director"}, {"name": "Tenkasi Ramanarayanan Seetharaman", "designation": "Ind. Non-Executive Director"}], "registrars": {"name": "Cameo Corporate Services Ltd.", "address1": "\"Subramanian Building\",\nNo.1, Vth Floor,\nClub Hous", "address2": "", "address3": "", "address4": "", "telephone": "044-28460390 (5 Lines)", "fax": "044-28460129", "email": "investor@cameoindia.com", "internet": "http://www.cameoindia.com", "city": "Chennai (Madras)", "state": "Tamil Nadu", "pincode": "600002"}, "listing": [{"name": "BSE 100", "value": "No"}, {"name": "BSE 200", "value": "No"}, {"name": "SENSEX", "value": "No"}, {"name": "CNX MIDCAP 200", "value": "No"}, {"name": "NIFTY 50", "value": "No"}, {"name": "BSE 500", "value": "No"}], "details": {"bseId": "515085", "nseId": "", "series": "", "isinid": "INE298E01022"}}