{"About the Company": "Finolex Cables Ltd is India`s largest and leading manufacturer of electrical and telecommunication cables.The company`s product range includes PVC insulated electrical wires and Flame Retardant Low Smoke electrical wires, PVC insulated single core and multicore industrial flexible cables, Rodent Repellent Multicore Flexible Cables, PVC Insulated Winding Wires and Core Flat Cables, XLPE Core Flat Cables, Power and Control Cables, High Voltage Power Cables,Polyethylene Insulated Jelly Filled Telephone Cables, Auto & Battery Cables, Co-axial and CATV cables, LAN Cables, Switchboard Cables, Fibre Optic Cables and others. .The company also in the business segment of Copper Rod, Electrical Cables, Communication Cables.", "address": {"address1": "26-27, Mumbai-Pune Road,", "address2": "Pimpri,,", "city": "Pune", "state": "Maharashtra", "pincode": "411018", "telephone1": "020-27506200", "telephone2": "020-27475963", "fax1": "020-27472239", "fax2": "", "email": "investors@finolex.com", "web": "http://www.finolex.com"}, "management": [{"name": "Deepak Chhabria", "designation": "Executive Chairman"}, {"name": "Ratnakar Prakash Barve", "designation": "Executive Director - Operations"}, {"name": "Nikhil Manohar Naik", "designation": "Non Executive Director"}, {"name": "Zubin Framroze Billimoria", "designation": "Independent Director"}, {"name": "Sriraman Raghuraman", "designation": "Independent Director"}], "registrars": {"name": "KFIN Technologies Pvt. Ltd.", "address1": "Selenium Tower B, Plot No. 31-32,", "address2": "Gachibowli, Financial District, \nNanakramguda,Seri", "address3": "", "address4": "", "telephone": "040-67161500, 67162222, 33211000", "fax": "040-23420814, 23001153", "email": "einward.ris@karvy.com", "internet": "http://www.kfintech.com", "city": "Hyderabad", "state": "Telangana", "pincode": "500032"}, "listing": [{"name": "BSE 100", "value": "No"}, {"name": "BSE 200", "value": "No"}, {"name": "SENSEX", "value": "No"}, {"name": "CNX MIDCAP 200", "value": "Yes"}, {"name": "NIFTY 50", "value": "No"}, {"name": "BSE 500", "value": "Yes"}], "details": {"bseId": "500144", "nseId": "FINCABLES", "series": "EQ", "isinid": "INE235A01022"}}