{"About the Company": "Phoenix Mills Ltd is engaged in the property development business.The business areas covered by the company includes Retail- Under this company is engaged into development of malls. Companys flagship development High Street Phoenix has emerged as the most frequented destination in Mumbai. The company has strategic alliance with Pantaloon group which owns major brands like Big Bazaar and Pantaloon. The company has developed malls under the name Phoenix Market City located at Mumbai, Pune, Bangalore and Chennai.Hospitality- Under this the company is engaged in developing 5 star hotels. The company has various ongoing projects under this segment located in Mumbai, Chennai, Pune and Agra.Entertainment-The company is engaged in development of entertainment zone such as multiplexes, gaming arcades, food courts and shopping centers.Commercial- Under this company has developed properties for commercial offices.", "address": {"address1": "462, Senapati Bapat Marg,", "address2": "Lower Parel,,", "city": "Mumbai", "state": "Maharashtra", "pincode": "400013", "telephone1": "022-24964307", "telephone2": "022-24964308", "fax1": "022-24938388", "fax2": "", "email": "investorrelations@highstreetphoenix.com", "web": "http://www.thephoenixmills.com"}, "management": [{"name": "Atul Ruia", "designation": "Chairman"}, {"name": "Shishir Shrivastava", "designation": "Managing Director"}, {"name": "Rajendra Kalkar", "designation": "Whole Time Director"}, {"name": "Rajesh Kulkarni", "designation": "Whole Time Director"}, {"name": "Amit Dabriwala", "designation": "Ind. Non-Executive Director"}], "registrars": {"name": "Link Intime India Pvt. Ltd.", "address1": "C 101, 247 Park,\nL.B.S. Marg, Vikhroli (West),", "address2": "", "address3": "", "address4": "", "telephone": "022-49186270, 49186200", "fax": "022-49186060", "email": "rnt.helpdesk@linkintime.co.in", "internet": "http://www.linkintime.co.in", "city": "Mumbai", "state": "Maharashtra", "pincode": "400083"}, "listing": [{"name": "BSE 100", "value": "No"}, {"name": "BSE 200", "value": "No"}, {"name": "SENSEX", "value": "No"}, {"name": "CNX MIDCAP 200", "value": "No"}, {"name": "NIFTY 50", "value": "No"}, {"name": "BSE 500", "value": "Yes"}], "details": {"bseId": "503100", "nseId": "PHOENIXLTD", "series": "EQ", "isinid": "INE211B01039"}}