{"About the Company": "Usha Martin started its business as a wire rope manufacturing company. The group has set new standards in the manufacture of wire rods, bright bars, steel wires, speciality wires, wire ropes, strand, conveyor cord, wire drawing and cable machinery..The company also in the business activities of Steel, Wire & Wire Ropes.", "address": {"address1": "2A, Shakespeare Sarani,", "address2": ",", "city": "Kolkata", "state": "West Bengal", "pincode": "700071", "telephone1": "033-71006300", "telephone2": "", "fax1": "033-71006400", "fax2": "", "email": "investor@ushamartin.co.in", "web": "http://www.ushamartin.com"}, "management": [{"name": "Vijay Singh Bapna", "designation": "Chairman & Ind.Dire (Non-Exe)"}, {"name": "Rajeev Jhawar", "designation": "Managing Director"}, {"name": "Sumit Kumar Modak", "designation": "Whole Time Director"}, {"name": "Tapas Gangopadhyay", "designation": "Non Executive Director"}, {"name": "V Ramakrishna Iyer", "designation": "Independent Director"}], "registrars": {"name": "MCS Share Transfer Agent Ltd.", "address1": "383 Lake Gardens,", "address2": "1st Floor,", "address3": "", "address4": "", "telephone": "033-40724051-54", "fax": "033-40724050", "email": "mcssta@rediffmail.com", "internet": "", "city": "Kolkata", "state": "West Bengal", "pincode": "700045"}, "listing": [{"name": "BSE 100", "value": "No"}, {"name": "BSE 200", "value": "No"}, {"name": "SENSEX", "value": "No"}, {"name": "CNX MIDCAP 200", "value": "No"}, {"name": "NIFTY 50", "value": "No"}, {"name": "BSE 500", "value": "Yes"}], "details": {"bseId": "517146", "nseId": "USHAMART", "series": "EQ", "isinid": "INE228A01035"}}