{"About the Company": "Indian Sucrose Ltd`s principal activity is to manufacture and exports White Crystal Sugar and its allied by product like Mollases, Bagasse, Alcohol and other Chemicals extracted from Sugar, also Manures, Breweries, Distilleries.The company also manufactures all kinds of Preserved food, Sauces, Jams, Alcoholic and Non Alcoholic Drinks and Pharmaceuticals, Sugar Cane, Sugar Beet and other Agricultural Products.", "address": {"address1": "G. T. Road,", "address2": "Mukerian,,", "city": "Hoshiarpur District", "state": "Punjab", "pincode": "144211", "telephone1": "01883-249002", "telephone2": "01883-249003", "fax1": "01883-244532", "fax2": "", "email": "isl.investor@yaducorporation.com", "web": "http://www.muksug.in"}, "management": [{"name": "Kunal Yadav", "designation": "Chairman & Executive Director"}, {"name": "Geeta Sharma", "designation": "Non Executive Director"}, {"name": "Jaitender Kumar", "designation": "Non Executive Director"}, {"name": "Neeraj Bansal", "designation": "Independent Director"}, {"name": "Shriram Agrawal", "designation": "Independent Director"}], "registrars": {"name": "MCS Share Transfer Agent Ltd.", "address1": "F-65, Ist Floor,\n Okhla Industrial Area, Phase-I,", "address2": "", "address3": "", "address4": "", "telephone": "011-41406149", "fax": "011-41709881", "email": "helpdeskdelhi@mcsregistrars.com", "internet": "http://www.mcsregistrars.com", "city": "New Delhi", "state": "Delhi", "pincode": "110020"}, "listing": [{"name": "BSE 100", "value": "No"}, {"name": "BSE 200", "value": "No"}, {"name": "SENSEX", "value": "No"}, {"name": "CNX MIDCAP 200", "value": "No"}, {"name": "NIFTY 50", "value": "No"}, {"name": "BSE 500", "value": "No"}], "details": {"bseId": "500319", "nseId": "OSWALSUG", "series": "", "isinid": "INE557C01017"}}