{"About the Company": "Jindal Capital Limited is has been registered as a Non-Banking Financial Company. The company invests in shares - both quoted and un quoted and Units of Mutual funds. Investments in capital market are mainly through reputed Portfolio Managers and on its own.Presently company is engaged in fund based activities and advisory services.", "address": {"address1": "201, Aggarwal Plaza,\n", "address2": "Sector-9,\n Rohini,,", "city": "Delhi", "state": "Delhi", "pincode": "110085", "telephone1": "011-45578272", "telephone2": "", "fax1": "011-", "fax2": "", "email": "info@jindalcapital.co.in", "web": "https://www.jindalcapital.co.in"}, "management": [{"name": "Sadhu Ram Aggarwal", "designation": "Chairman & Managing Director"}, {"name": "Divya Aggarwal", "designation": "Executive Director & CFO"}, {"name": "Udit Aggarwal", "designation": "Non Executive Director"}, {"name": "Baij Nath Gupta", "designation": "Ind. Non-Executive Director"}, {"name": "Sham Lal Singal", "designation": "Ind. Non-Executive Director"}], "registrars": {"name": "Link Intime India Pvt. Ltd.", "address1": "Noble Heights, Ist Floor, \nPlot NH 2, C-1 Block LS", "address2": "", "address3": "", "address4": "", "telephone": "011-49411000", "fax": "011-41410591", "email": "delhi@linkintime.co.in", "internet": "http://www.linkintime.co.in", "city": "New Delhi", "state": "Delhi", "pincode": "110058"}, "listing": [{"name": "BSE 100", "value": "No"}, {"name": "BSE 200", "value": "No"}, {"name": "SENSEX", "value": "No"}, {"name": "CNX MIDCAP 200", "value": "No"}, {"name": "NIFTY 50", "value": "No"}, {"name": "BSE 500", "value": "No"}], "details": {"bseId": "530405", "nseId": "", "series": "", "isinid": "INE356F01017"}}