{"About the Company": "Century Enka Ltd manufactures nylon and other man-made fibres and fabrics. Nylon yarn is marketed in India under the trade mark Enkalon. The company produces jumbo beams, specialty yarns, industrial/fiber grade chips, industrial yarns and tyre-cord fabrics. Their yarns are used as reinforcing material in tyres, conveyor belts, V-belts, hoses, ropes and cordage, and broad and narrow woven. Their product range includes wide range of high quality Nylon Processed Yarns for varied application areas,in weaving segment it provides Mono Filaments and Multi filaments,Specialized Product Range for High TPM Fabrics (Georgette/Chiffons),Nylon POY For Air Texturising,Sewing Thread & Fish Net,Polyester Filament Yarn- companys RAJASHREE brand has now become synonymous with highest quality POY products,Warping applications,Processed Yarn and Industrial Yarn & Tyer Cord Fabric. They have introduced for the first time in India Nylon Flat Yarn on paper tube packages, produced from latest generation Draw-Winder machines.", "address": {"address1": "Plot No. 72 & 72-A,", "address2": "MIDC, Bhosari,,", "city": "Pune", "state": "Maharashtra", "pincode": "411026", "telephone1": "020-66127304", "telephone2": "", "fax1": "020-27120113", "fax2": "", "email": "cel.registeredoffice@birlacentury.com", "web": "http://www.centuryenka.com"}, "management": [{"name": "Rajashree Birla", "designation": "Chairperson & Executive Director"}, {"name": "Suresh Sodani", "designation": "Managing Director"}, {"name": "Krupa R Gandhi", "designation": "Independent Director"}, {"name": "Devajyoti N Bhattacharya", "designation": "Non Executive Director"}, {"name": "Sohanlal K Jain", "designation": "Independent Director"}], "registrars": {"name": "Link Intime India Pvt. Ltd.", "address1": "C 101, 247 Park,\nL.B.S. Marg, Vikhroli (West),", "address2": "", "address3": "", "address4": "", "telephone": "022-49186270, 49186200", "fax": "022-49186060", "email": "rnt.helpdesk@linkintime.co.in", "internet": "http://www.linkintime.co.in", "city": "Mumbai", "state": "Maharashtra", "pincode": "400083"}, "listing": [{"name": "BSE 100", "value": "No"}, {"name": "BSE 200", "value": "No"}, {"name": "SENSEX", "value": "No"}, {"name": "CNX MIDCAP 200", "value": "Yes"}, {"name": "NIFTY 50", "value": "No"}, {"name": "BSE 500", "value": "No"}], "details": {"bseId": "500280", "nseId": "CENTENKA", "series": "EQ", "isinid": "INE485A01015"}}