{"About the Company": "Damodar Industries Ltd has a completely integrated and advanced production line for manufacturing fancy and speciality yarns.The company is engaged in spinning, draw-texturising, air-texturising, fancy doubling and yarn dyeing. The company has in-house manufacturing operations, which are essential building bricks of fashion. Product range of the company includes:Cotton Yarn,Fancy Yarn,Blended Fancy Yarn,Product Enquiry,Spun yarn in polyester/viscose and silk/polyester in various counts.", "address": {"address1": "19/22 & 27/30, Madhu Estate,", "address2": ",", "city": "Mumbai", "state": "Maharashtra", "pincode": "400013", "telephone1": "22-66610301", "telephone2": "22-66610302", "fax1": "22-66610308", "fax2": "", "email": "cs@damodargroup.com", "web": "http://www.damodargroup.com"}, "management": [{"name": "Arunkumar Biyani", "designation": "Chairman"}, {"name": "Ajay D Biyani", "designation": "Managing Director"}, {"name": "Anil D Biyani", "designation": "Executive Director"}, {"name": "Ketan K Patel", "designation": "Independent Director"}, {"name": "Mamta A Biyani", "designation": "Independent Director"}], "registrars": {"name": "Link Intime India Pvt. Ltd.", "address1": "C 101, 247 Park,\nL.B.S. Marg, Vikhroli (West),", "address2": "", "address3": "", "address4": "", "telephone": "022-49186270, 49186200", "fax": "022-49186060", "email": "rnt.helpdesk@linkintime.co.in", "internet": "http://www.linkintime.co.in", "city": "Mumbai", "state": "Maharashtra", "pincode": "400083"}, "listing": [{"name": "BSE 100", "value": "No"}, {"name": "BSE 200", "value": "No"}, {"name": "SENSEX", "value": "No"}, {"name": "CNX MIDCAP 200", "value": "No"}, {"name": "NIFTY 50", "value": "No"}, {"name": "BSE 500", "value": "No"}], "details": {"bseId": "521220", "nseId": "DAMODARIND", "series": "EQ", "isinid": "INE497D01022"}}