{"About the Company": "Mudra Lifestyle Limited is an India-based integrated textile company. The Company is engaged in manufacturing of textiles consisting of fabric and garments. The Company manufactures fabrics and garments for domestic and export market. The Companys product portfolio includes finished fabric, processing and garments.", "address": {"address1": "16/2B, Sri Vinayaka Indl Estate,", "address2": "Singasandra, Near Dakshin Honda Showroom,Hosur Road,", "city": "Bengaluru", "state": "Karnataka", "pincode": "560068", "telephone1": "080-42548800", "telephone2": "", "fax1": "080-", "fax2": "", "email": "investor@elandapparel.com", "web": "http://www.elandapparel.com"}, "management": [{"name": "Dong Ju Kim", "designation": "Chairman & Managing Director"}, {"name": "Chong Tae Baek", "designation": "Independent Director"}, {"name": "Sivabalan Paul Pandian", "designation": "Independent Director"}, {"name": "Elizabeth Ravi", "designation": "Independent Director"}], "registrars": {"name": "Bigshare Services Pvt. Ltd.", "address1": "1st Floor, Bharat Tin Works Building,", "address2": "Opp. Vasant Oasis, Makwana Road, Marol,,", "address3": "Andheri (East),", "address4": "", "telephone": "022-62638200", "fax": "022-62638299", "email": "investor@bigshareonline.com", "internet": "http://www.bigshareonline.com", "city": "Mumbai", "state": "Maharashtra", "pincode": "400059"}, "listing": [{"name": "BSE 100", "value": "No"}, {"name": "BSE 200", "value": "No"}, {"name": "SENSEX", "value": "No"}, {"name": "CNX MIDCAP 200", "value": "No"}, {"name": "NIFTY 50", "value": "No"}, {"name": "BSE 500", "value": "No"}], "details": {"bseId": "532820", "nseId": "ELAND", "series": "", "isinid": "INE311H01018"}}