{"About the Company": "Jattashankar Industries Ltd was originally incorporated as Jatta Poly Yarn Private Limited in the year 1988 for setting up a texturising and twisting plant at Silvassa in the Union Territory of Dadra & Nagar Haveli. They are one of the leading manufacturer of Polyester Dyed Yarn in India. Company is catering to diverse requirements of Synthetic Yarns consumers, for the end use like Woven Fabrics - Suitings, Shirtings, Sarees & Dress materials, Hosiery & Knitwear, Furnishing & Upholstery fabrics, Narrow Fabrics  Labels, Laces, Tapes & Elastics, Sewing Thread, and Industrial Fabrics.", "address": {"address1": "11, Parasrampuria Apartment,", "address2": "Filmcity Road,Opp. Bank of India,,Gokuldham, Goregaon (East),", "city": "Mumbai", "state": "Maharashtra", "pincode": "400063", "telephone1": "022-28414262", "telephone2": "022-28414265", "fax1": "022-28414269", "fax2": "", "email": "jattashankarind@yahoo.com", "web": "http://www.jsil.in"}, "management": [{"name": "Jattashankar Poddar", "designation": "Chairman & Managing Director"}, {"name": "Sharad Poddar", "designation": "Executive Director"}, {"name": "Sandeepkumar Modi", "designation": "Independent Director"}, {"name": "Udit Master", "designation": "Independent Director"}, {"name": "Richa Sushil Chaudhary", "designation": "Independent Woman Director"}], "registrars": {"name": "Link Intime India Pvt. Ltd.", "address1": "C 101, 247 Park,\nL.B.S. Marg, Vikhroli (West),", "address2": "", "address3": "", "address4": "", "telephone": "022-49186270, 49186200", "fax": "022-49186060", "email": "rnt.helpdesk@linkintime.co.in", "internet": "http://www.linkintime.co.in", "city": "Mumbai", "state": "Maharashtra", "pincode": "400083"}, "listing": [{"name": "BSE 100", "value": "No"}, {"name": "BSE 200", "value": "No"}, {"name": "SENSEX", "value": "No"}, {"name": "CNX MIDCAP 200", "value": "No"}, {"name": "NIFTY 50", "value": "No"}, {"name": "BSE 500", "value": "No"}], "details": {"bseId": "514318", "nseId": "", "series": "", "isinid": "INE722N01014"}}