{"About the Company": "Rajvir Industries Ltd.is engaged in the production of organic cotton yarn products which include 100% organic cot, organic cot in blends with Indian cot (5%, 10%, 15% & 20%) and organic cotton in blends with modal / viscose / poly.The product range of the company includes Cotton and Cotton Blends,Melange Synthetic,Modal Dyed Products,Compact Yarn,Silk Product,Wool and Flame Retardent.", "address": {"address1": "1st Floor, Surya Towers,", "address2": "105, Sardar Patel Road,,", "city": "Secunderabad", "state": "Telangana", "pincode": "500003", "telephone1": "040-6225555", "telephone2": "040-27845628", "fax1": "040-27840656", "fax2": "", "email": "rajvir@rajvirindustrieslimited.com", "web": "http://www.rajvirindustrieslimited.com"}, "management": [{"name": "Upender Kumar Agarwal", "designation": "Chairman"}, {"name": "Ritesh Kumar Agarwal", "designation": "Managing Director"}, {"name": "Sheetal B Dave", "designation": "Independent Director"}, {"name": "Ritesh Agrawal", "designation": "Independent Director"}, {"name": "Sudhakar Kanneboyina", "designation": "Independent Director"}], "registrars": {"name": "XL Softech Systems Ltd.", "address1": "No. 3, Sagar View Society,", "address2": "Road No. 2,,", "address3": "Banjara Hills,", "address4": "", "telephone": "040-23545913, 23545914, 23545915", "fax": "040-23553214", "email": "xlsoftech@hdl.vsnl.net.in", "internet": "http://www.xlsoftech.com", "city": "Hyderabad", "state": "Telangana", "pincode": "500034"}, "listing": [{"name": "BSE 100", "value": "No"}, {"name": "BSE 200", "value": "No"}, {"name": "SENSEX", "value": "No"}, {"name": "CNX MIDCAP 200", "value": "No"}, {"name": "NIFTY 50", "value": "No"}, {"name": "BSE 500", "value": "No"}], "details": {"bseId": "532665", "nseId": "RAJVIR", "series": "", "isinid": "INE011H01014"}}