{"About the Company": "Sangam (India) Ltd is engaged in the manufacturing of yarn and fabrics", "address": {"address1": "Post Box No. 90,", "address2": "Atun, Chittorgarh Road,,", "city": "Bhilwara", "state": "Rajasthan", "pincode": "311001", "telephone1": "01482-245400-06", "telephone2": "", "fax1": "01482-245450", "fax2": "", "email": "secretarial@sangamgroup.com", "web": "http://www.sangamgroup.com"}, "management": [{"name": "R P Soni", "designation": "Chairman"}, {"name": "S N Modani", "designation": "Managing Director & CEO"}, {"name": "V K Sodani", "designation": "Executive Director"}, {"name": "Anurag Soni", "designation": "Director & CFO"}, {"name": "Yaduvendra Mathur", "designation": "Independent Director"}], "registrars": {"name": "Bigshare Services Pvt. Ltd.", "address1": "1st Floor, Bharat Tin Works Building,", "address2": "Opp. Vasant Oasis, Makwana Road, Marol,,", "address3": "Andheri (East),", "address4": "", "telephone": "022-62638200", "fax": "022-62638299", "email": "investor@bigshareonline.com", "internet": "http://www.bigshareonline.com", "city": "Mumbai", "state": "Maharashtra", "pincode": "400059"}, "listing": [{"name": "BSE 100", "value": "No"}, {"name": "BSE 200", "value": "No"}, {"name": "SENSEX", "value": "No"}, {"name": "CNX MIDCAP 200", "value": "No"}, {"name": "NIFTY 50", "value": "No"}, {"name": "BSE 500", "value": "No"}], "details": {"bseId": "514234", "nseId": "SANGAMIND", "series": "EQ", "isinid": "INE495C01010"}}