{"About the Company": "Wheel & Axle Textiles Ltd is engaged in the business of textile.", "address": {"address1": "820, Golden Point,", "address2": "Nr Telephone Exchange Begampura,,Falsawadi, Ring Road,", "city": "Surat", "state": "Gujarat", "pincode": "395003", "telephone1": "0261-2455425", "telephone2": "0261-2455426", "fax1": "0261-2211213", "fax2": "", "email": "shantaiindustriesltd@gmail.com", "web": "http://www.shantaiindustrieslimited.com"}, "management": [{"name": "Harish F Sawlani", "designation": "Chairman & Managing Director"}, {"name": "Vasudev F Sawlani", "designation": "Whole Time Director"}, {"name": "Reena H Sawlani", "designation": "Non Executive Director"}, {"name": "Vandanaben Satishbhai Dalal", "designation": "Ind. Non-Executive Director"}, {"name": "Omprakash Vishandas Lakhwani", "designation": "Ind. Non-Executive Director"}], "registrars": {"name": "MCS Share Transfer Agent Ltd.", "address1": "1st Floor, Neelam Appartment, \n88 Sampatrao Colony", "address2": "", "address3": "", "address4": "", "telephone": "0265-2314757", "fax": "0265-2341639", "email": "mcsltdbaroda@gmail.com", "internet": "http://www.mcsregistrars.com", "city": "Vadodra", "state": "Gujarat", "pincode": "390021"}, "listing": [{"name": "BSE 100", "value": "No"}, {"name": "BSE 200", "value": "No"}, {"name": "SENSEX", "value": "No"}, {"name": "CNX MIDCAP 200", "value": "No"}, {"name": "NIFTY 50", "value": "No"}, {"name": "BSE 500", "value": "No"}], "details": {"bseId": "512297", "nseId": "", "series": "", "isinid": "INE408F01016"}}