{"About the Company": "Winsome Yarns Ltd is one of the largest producer of Melange Yarn in India,they produce Melange Yarn for circular knitting, socks, weaving and knitwear.The company also offers Gassed Mercerised Melange.The product range of the company includes 100% Cotton,100% Acrylic,Cotton Blends with Viscose,Polyester,Modal,Silk,etc.", "address": {"address1": "SCO- 191-192,", "address2": "Sector 34-A,,", "city": "Chandigarh", "state": "Chandigarh", "pincode": "160022", "telephone1": "0172-2603966", "telephone2": "0172-4612000", "fax1": "0172-4614000", "fax2": "", "email": "cshare@winsomegroup.com", "web": "http://www.winsomegroup.com"}, "management": [{"name": "Manish Bagrodia", "designation": "Exe.Chairman & Mng.Director"}, {"name": "Mridula Goyal", "designation": "Non Exe.Non Ind.Director"}, {"name": "Rajiv Chadha", "designation": "Ind. Non-Executive Director"}, {"name": "Tilak Raj Dembla", "designation": "Ind. Non-Executive Director"}, {"name": "Pankaj Mahajan", "designation": "Ind. Non-Executive Director"}], "registrars": {"name": "Link Intime India Pvt. Ltd.", "address1": "Noble Heights, Ist Floor, \nPlot NH 2, C-1 Block LS", "address2": "", "address3": "", "address4": "", "telephone": "011-49411000", "fax": "011-41410591", "email": "delhi@linkintime.co.in", "internet": "http://www.linkintime.co.in", "city": "New Delhi", "state": "Delhi", "pincode": "110058"}, "listing": [{"name": "BSE 100", "value": "No"}, {"name": "BSE 200", "value": "No"}, {"name": "SENSEX", "value": "No"}, {"name": "CNX MIDCAP 200", "value": "No"}, {"name": "NIFTY 50", "value": "No"}, {"name": "BSE 500", "value": "No"}], "details": {"bseId": "514348", "nseId": "WINSOME", "series": "BE", "isinid": "INE784B01035"}}