{"About the Company": "Birla Corporation Ltd (BCL) operates in four divisions namely cement, jute, vinoleum and auto trim division.The company manufactures ordinary portland cement ,fly ash- based portland pozzolana cement portland slag cement and sulphate resistant cement,jute fibre that is eco-friendly and bio degradable, cushion vinyl flooring and PVC Sheet and door trims for automobile industry.The company also engagged in the business of Jute, Cement.", "address": {"address1": "'\"Birla Building',\n'", "address2": "3rd & 4th Floor,,\n9/1 R N Mukherjee Road,", "city": "Kolkata", "state": "West Bengal", "pincode": "700001", "telephone1": "033-66166729", "telephone2": "033-66166737", "fax1": "033-22482872", "fax2": "033-22487988", "email": "investorsgrievance@birlacorp.com", "web": "http://www.birlacorporation.com"}, "management": [{"name": "Harsh V Lodha", "designation": "Chairman"}, {"name": "Sandip Ghose", "designation": "Managing Director & CEO"}, {"name": "Dilip Ganesh Karnik", "designation": "Director"}, {"name": "Vikram Swarup", "designation": "Director"}, {"name": "Anand Bordia", "designation": "Director"}], "registrars": {"name": "MCS Share Transfer Agent Ltd.", "address1": "383 Lake Gardens,", "address2": "1st Floor,", "address3": "", "address4": "", "telephone": "033-40724051-54", "fax": "033-40724050", "email": "mcssta@rediffmail.com", "internet": "", "city": "Kolkata", "state": "West Bengal", "pincode": "700045"}, "listing": [{"name": "BSE 100", "value": "No"}, {"name": "BSE 200", "value": "No"}, {"name": "SENSEX", "value": "No"}, {"name": "CNX MIDCAP 200", "value": "Yes"}, {"name": "NIFTY 50", "value": "No"}, {"name": "BSE 500", "value": "Yes"}], "details": {"bseId": "500335", "nseId": "BIRLACORPN", "series": "EQ", "isinid": "INE340A01012"}}