{"About the Company": "Hexaware Technologies Ltd is an IT and Process outsourcing service provider in global space. The company provides technological solutions and specialises in Business Intelligence, Business Analytics, Enterprise Applications, Transportation, HR-IT and Legacy Modernization.", "address": {"address1": "152, Millennium Business Park,", "address2": "Sector - lll, \u2018A\u2019 Block,,TTC Industrial Area,", "city": "New Mumbai", "state": "Maharashtra", "pincode": "400710", "telephone1": "022-41599595", "telephone2": "", "fax1": "022-41599578", "fax2": "", "email": "investori@hexaware.com", "web": "http://www.hexaware.com"}, "management": [{"name": "Atul K Nishar", "designation": "Chairman"}, {"name": "Jimmy Mahtani", "designation": "Vice Chairman"}, {"name": "R Srikrishna", "designation": "Executive Director & CEO"}, {"name": "Kosmas Kalliarekos", "designation": "Director"}, {"name": "P R Chandrasekar", "designation": "Ind. Non-Executive Director"}], "registrars": {"name": "KFIN Technologies Pvt. Ltd.", "address1": "Selenium Tower B, Plot No. 31-32,", "address2": "Gachibowli, Financial District, \nNanakramguda,Seri", "address3": "", "address4": "", "telephone": "040-67161500, 67162222, 33211000", "fax": "040-23420814, 23001153", "email": "einward.ris@karvy.com", "internet": "http://www.kfintech.com", "city": "Hyderabad", "state": "Telangana", "pincode": "500032"}, "listing": [{"name": "BSE 100", "value": "No"}, {"name": "BSE 200", "value": "No"}, {"name": "SENSEX", "value": "No"}, {"name": "CNX MIDCAP 200", "value": "Yes"}, {"name": "NIFTY 50", "value": "No"}, {"name": "BSE 500", "value": "No"}], "details": {"bseId": "532129", "nseId": "HEXAWARE", "series": "", "isinid": "INE093A01033"}}