{"About the Company": "Dhanuka Commercial Ltd was incorporated on November 16, 1994. It is a Non Deposit taking Non-systemically Important Non Banking Finance Company (NBFC-ND-NSI) engaged primarily in the business of advancing loans and investing/trading in securities.", "address": {"address1": "523-A, Somdutt Chamber-II,", "address2": "9, Bhikaji Cama Place,,", "city": "New Delhi", "state": "Delhi", "pincode": "110066", "telephone1": "011-45657452", "telephone2": "", "fax1": "011-", "fax2": "", "email": "info@moneyboxxfinance.com", "web": "http://www.moneyboxxfinance.com"}, "management": [{"name": "Uma Shankar Paliwal", "designation": "Chairman & Ind.Dire (Non-Exe)"}, {"name": "Deepak Aggarwal", "designation": "Whole Time Director"}, {"name": "Mayur Modi", "designation": "Whole Time Director"}, {"name": "Atul Garg", "designation": "Non Exe.Non Ind.Director"}, {"name": "Govind Gupta", "designation": "Non Exe.Non Ind.Director"}], "registrars": {"name": "Mas Services Ltd.", "address1": "T-34, 2nd Floor,", "address2": "Oklha Industrial Area,,", "address3": "Phase - II,", "address4": "", "telephone": "011-26387281, 26387282, 26387283", "fax": "011-26387384", "email": "info@masserv.com", "internet": "http://www.masserv.com", "city": "New Delhi", "state": "Delhi", "pincode": "110020"}, "listing": [{"name": "BSE 100", "value": "No"}, {"name": "BSE 200", "value": "No"}, {"name": "SENSEX", "value": "No"}, {"name": "CNX MIDCAP 200", "value": "No"}, {"name": "NIFTY 50", "value": "No"}, {"name": "BSE 500", "value": "No"}], "details": {"bseId": "538446", "nseId": "", "series": "", "isinid": "INE296Q01012"}}