{"About the Company": "Amrapali Industries Ltd is engaged in the bullion business along with the corporate membership of the Multi Commodity Exchange of India (MCX), National Commoditiesand Derivatives Exchange of India (NCDEX) and Ahmedabad Commodity Exchange.", "address": {"address1": "Unit No. PO5-02E, 5th Floor,", "address2": "Tower A WTC Gift City,,", "city": "Gandhinagar", "state": "Gujarat", "pincode": "382355", "telephone1": "02712-26581329", "telephone2": "", "fax1": "02712-26579169", "fax2": "02712-26584313", "email": "ail@amrapali.com", "web": "http://www.amrapalispot.com"}, "management": [{"name": "Yashwant Amratlal Thakkar", "designation": "Chairman & Managing Director"}, {"name": "Rashmikant Amratlal Thakkar", "designation": "Executive Director"}, {"name": "Bhumi Atit Patel", "designation": "Non Exe.Non Ind.Director"}, {"name": "Mayur Rajendrabhai Parikh", "designation": "Ind. Non-Executive Director"}, {"name": "Haresh Jashubhai Chaudhari", "designation": "Ind. Non-Executive Director"}], "registrars": {"name": "Purva Sharegistry (india) Pvt. Ltd.", "address1": "No.9, Ground Floor,\nShiv Shakti Industrial Estate,", "address2": "", "address3": "", "address4": "", "telephone": "022-23016761, 23018261", "fax": "022-23012517", "email": "support@purvashare.com", "internet": "http://www.purvashare.com", "city": "Mumbai", "state": "Maharashtra", "pincode": "400011"}, "listing": [{"name": "BSE 100", "value": "No"}, {"name": "BSE 200", "value": "No"}, {"name": "SENSEX", "value": "No"}, {"name": "CNX MIDCAP 200", "value": "No"}, {"name": "NIFTY 50", "value": "No"}, {"name": "BSE 500", "value": "No"}], "details": {"bseId": "526241", "nseId": "", "series": "", "isinid": "INE762C01021"}}