{"About the Company": "Data is not Available", "address": {"address1": "C/18, Mulund Sahakar Vishwa CHS,", "address2": "Nahur Road,,Sarvodaya Nagar,", "city": "Mumbai", "state": "Maharashtra", "pincode": "400080", "telephone1": "022-23431914", "telephone2": "", "fax1": "022-", "fax2": "", "email": "jashdealmark@gmail.com", "web": "http://www.jashdealmark.com"}, "management": [{"name": "Shailendra Jayantilal Khona", "designation": "Managing Director"}, {"name": "Praful Jayantilal Khona", "designation": "Executive Director"}, {"name": "Dipti Shailendra Khona", "designation": "Executive Director"}, {"name": "Vipulchandra Sureshchandra Acharya", "designation": "Independent Director"}, {"name": "Sumeet Pravinchandra Ghuntla", "designation": "Independent Director"}], "registrars": {"name": "Purva Sharegistry (india) Pvt. Ltd.", "address1": "No.9, Ground Floor,\nShiv Shakti Industrial Estate,", "address2": "", "address3": "", "address4": "", "telephone": "022-23016761, 23018261", "fax": "022-23012517", "email": "support@purvashare.com", "internet": "http://www.purvashare.com", "city": "Mumbai", "state": "Maharashtra", "pincode": "400011"}, "listing": [{"name": "BSE 100", "value": "No"}, {"name": "BSE 200", "value": "No"}, {"name": "SENSEX", "value": "No"}, {"name": "CNX MIDCAP 200", "value": "No"}, {"name": "NIFTY 50", "value": "No"}, {"name": "BSE 500", "value": "No"}], "details": {"bseId": "540394", "nseId": "", "series": "", "isinid": "INE801W01017"}}