{"About the Company": "Triveni Enterprises Ltd is to carry on the business of dealers, general order suppliers, contractors, importers, exporters, merchants stockiest, buyers, sellers, growers, agents, brokers, commission agents, and dealers in cotton, jute, tea, coffee, rubber, oil, grains, pulses, seeds, vegetable product, cotton goods, jute goods, textiles, garments, yarn, synthetic goods, fibourous materials, mill stores, coal, chemicals, fertilizers, building materials, office appliances, Domestic appliances, furnitures, Decorative items, gift items, steels, utensils, plastic goods, rubber items, pulp, paper, engineering goods, all kinds of electrical and electronics items, including chandelier, lamp shades and other decorative items.", "address": {"address1": "Shop No.7 (8,9),", "address2": "Mamata Anand, Jankul,,Nashik Pune,", "city": "Nasik", "state": "Maharashtra", "pincode": "422101", "telephone1": "", "telephone2": "", "fax1": "022-", "fax2": "", "email": "trivenienterprisesltd@gmail.com", "web": "http://www.trivenienterprisesltd.com"}, "management": [{"name": "Ramchandra Ramhit Varma", "designation": "Director"}, {"name": "Pintu", "designation": "Director"}, {"name": "Arvind Kumar Gupta", "designation": "Director"}], "registrars": {"name": "Universal Capital Securities Pvt. Ltd.", "address1": "C 101, 247 Park, LBS Road, Vikhroli West,", "address2": "", "address3": "", "address4": "", "telephone": "022-28207203, 28207204, 28207205", "fax": "022-28207207", "email": "info@unisec.in", "internet": "http://www.unisec.in", "city": "Mumbai", "state": "Maharashtra", "pincode": "400083"}, "listing": [{"name": "BSE 100", "value": "No"}, {"name": "BSE 200", "value": "No"}, {"name": "SENSEX", "value": "No"}, {"name": "CNX MIDCAP 200", "value": "No"}, {"name": "NIFTY 50", "value": "No"}, {"name": "BSE 500", "value": "No"}], "details": {"bseId": "538569", "nseId": "", "series": "", "isinid": "INE916P01025"}}