{"About the Company": "India Cements Ltd is the largest manufacturer of cement in South India.The product range of the company includes Ready to Mix concrete ,Coromandel King, Sankar Sakthi and Raasi Gold OPC (Ordinary Portland Cement) which are high strength cement used for building runways, concrete roads and bridges,Coromandel Super Power, Sankar Super Power and Raasi Super Power range of blended cement are high durability cement, suited for plastering and finishing works,Sankar SRC (Sulphate Resisting Portland Cement) is basically used for construction of basements, coastal works, chemical factories, water treatment plants, etc.", "address": {"address1": "\"Dhun Building\"", "address2": "827, Anna Salai,,", "city": "Chennai (Madras)", "state": "Tamil Nadu", "pincode": "600002", "telephone1": "044-28521526", "telephone2": "044-28572100", "fax1": "044-28520638", "fax2": "044-28517198", "email": "investor@indiacements.co.in", "web": "http://www.indiacements.co.in"}, "management": [{"name": "N Srinivasan", "designation": "Vice Chairman & Mng.Director"}, {"name": "Rupa Gurunath", "designation": "Whole Time Director"}, {"name": "Chitra Srinivasan", "designation": "Director"}, {"name": "S Balasubramanian Adityan", "designation": "Director"}, {"name": "Lakshmi Aparna Sreekumar", "designation": "Director"}], "registrars": {"name": "Integrated Registry Management Services Pvt. Ltd.", "address1": "2nd Floor, Kences Towers,\n1, Ramakrishna Street,\nN", "address2": "", "address3": "", "address4": "", "telephone": "044-28140484", "fax": "", "email": "kences@integratedindia.in", "internet": "https://www.integratedindia.in", "city": "Chennai (Madras)", "state": "Tamil Nadu", "pincode": "600017"}, "listing": [{"name": "BSE 100", "value": "No"}, {"name": "BSE 200", "value": "No"}, {"name": "SENSEX", "value": "No"}, {"name": "CNX MIDCAP 200", "value": "Yes"}, {"name": "NIFTY 50", "value": "No"}, {"name": "BSE 500", "value": "Yes"}], "details": {"bseId": "530005", "nseId": "INDIACEM", "series": "EQ", "isinid": "INE383A01012"}}